{
  "app": "member",
  "title": "Foundr1 MEMBER",
  "packageName": "jp.foundr1.member",
  "versionName": "0.1.4",
  "versionCode": 4,
  "releaseLabel": "2026.06.18.4",
  "buildType": "debug",
  "fileName": "foundr1-member-0.1.4.apk",
  "downloadPath": "/downloads/member/foundr1-member-0.1.4.apk",
  "latestDownloadPath": "/downloads/member/latest.apk",
  "legacyDownloadPath": "/downloads/foundr1-member-latest.apk",
  "sizeBytes": 848645,
  "sha256": "7736c5df6c6adb67f203193271c3483dda5cdd93b4e5743f959aa70611359874",
  "builtAt": "2026-06-18T04:26:15.667Z",
  "gitCommit": "89edb2d",
  "gitSubject": "Fix Android status bar contrast for Member"
}
